MANIFEST.in
README.rst
setup.cfg
setup.py
pyuhooair/__init__.py
pyuhooair/auth.py
pyuhooair/data.py
pyuhooair/objects.py
pyuhooair.egg-info/PKG-INFO
pyuhooair.egg-info/SOURCES.txt
pyuhooair.egg-info/dependency_links.txt
pyuhooair.egg-info/entry_points.txt
pyuhooair.egg-info/requires.txt
pyuhooair.egg-info/top_level.txt