Metadata-Version: 1.1
Name: pyuhooair
Version: 0.0.2
Summary: Python binding for uHoo Air Quality Device API
Home-page: https://github.com/netmanchris/pyuhooair
Author: netmanchris
Author-email: chris_young@me.com
License: Apache2
Keywords: uHooair uHoo Air
Platform: UNKNOWN
Classifier: Development Status :: 3 - Alpha
Classifier: Intended Audience :: Developers
Classifier: Intended Audience :: System Administrators
Classifier: License :: OSI Approved :: Apache Software License
Classifier: Programming Language :: Python
Classifier: Natural Language :: English
Classifier: Operating System :: OS Independent
Classifier: Topic :: Software Development :: Libraries :: Python Modules
